gpustack_runner/__init__.py
gpustack_runner/__main__.py
gpustack_runner/__utils__.py
gpustack_runner/_version.py
gpustack_runner/_version.pyi
gpustack_runner/envs.py
gpustack_runner/runner.py
gpustack_runner/runner.py.json
gpustack_runner/cmds/__init__.py
gpustack_runner/cmds/__types__.py
gpustack_runner/cmds/images.py
gpustack_runner/_version_appendix.py
gpustack_runner-0.1.24.post4.dist-info/METADATA
gpustack_runner-0.1.24.post4.dist-info/WHEEL
gpustack_runner-0.1.24.post4.dist-info/entry_points.txt
gpustack_runner-0.1.24.post4.dist-info/licenses/LICENSE
gpustack_runner-0.1.24.post4.dist-info/RECORD
