Metadata-Version: 2.4
Name: gpustack-runner
Version: 0.1.24.post4
Summary: GPUStack Runner is library for registering runnable accelerated backends and services in GPUStack.
Project-URL: Homepage, https://github.com/gpustack/runner
Project-URL: Bug Tracker, https://github.com/gpustack/gpustack/issues
Author-email: GPUStack Authors <contact@gpustack.ai>
License-Expression: Apache-2.0
License-File: LICENSE
Classifier: Programming Language :: Python :: 3
Classifier: Programming Language :: Python :: 3.10
Classifier: Programming Language :: Python :: 3.11
Classifier: Programming Language :: Python :: 3.12
Classifier: Programming Language :: Python :: 3.13
Requires-Python: >=3.10
Requires-Dist: argcomplete>=3.6.3
Requires-Dist: dataclasses-json>=0.6.7
Requires-Dist: requests>=2.32.3
